LICENSE
paypi/__init__.py
paypi/main.py
paypi/user.py
paypi-1.0.8.dist-info/LICENSE
paypi-1.0.8.dist-info/WHEEL
paypi-1.0.8.dist-info/METADATA
paypi-1.0.8.dist-info/RECORD
