Metadata-Version: 2.1
Name: paypi
Version: 1.0.8
Summary: Official PayPI Partner Library
Home-page: https://paypi.dev
License: MIT
Keywords: paypi
Author: PayPI
Author-email: hello@paypi.dev
Requires-Python: >=3.6,<4.0
Classifier: License :: OSI Approved :: MIT License
Classifier: Programming Language :: Python :: 3
Classifier: Programming Language :: Python :: 3.6
Classifier: Programming Language :: Python :: 3.7
Classifier: Programming Language :: Python :: 3.8
Classifier: Programming Language :: Python :: 3.9
Requires-Dist: aiohttp (>=3.7.4,<4.0.0)
Requires-Dist: gql[aiohttp] (==3.0.0a6)
Project-URL: Repository, https://github.com/paypi/paypi-python
